jupyter_remote_desktop_proxy/__init__.py
jupyter_remote_desktop_proxy/handlers.py
jupyter_remote_desktop_proxy/server_extension.py
jupyter_remote_desktop_proxy/setup_websockify.py
jupyter_remote_desktop_proxy/share/xstartup
jupyter_remote_desktop_proxy/static/clipboard.svg
jupyter_remote_desktop_proxy/static/jupyter-logo.svg
jupyter_remote_desktop_proxy/static/dist/index.css
jupyter_remote_desktop_proxy/static/dist/index.css.map
jupyter_remote_desktop_proxy/static/dist/viewer.js
jupyter_remote_desktop_proxy/static/dist/viewer.js.LICENSE.txt
jupyter_remote_desktop_proxy/static/dist/viewer.js.map
jupyter_remote_desktop_proxy/templates/index.html
jupyter_remote_desktop_proxy-3.0.1.data/data/etc/jupyter/jupyter_notebook_config.d/jupyter_remote_desktop_proxy.json
jupyter_remote_desktop_proxy-3.0.1.data/data/etc/jupyter/jupyter_server_config.d/jupyter_remote_desktop_proxy.json
jupyter_remote_desktop_proxy-3.0.1.dist-info/licenses/LICENSE
jupyter_remote_desktop_proxy-3.0.1.dist-info/METADATA
jupyter_remote_desktop_proxy-3.0.1.dist-info/WHEEL
jupyter_remote_desktop_proxy-3.0.1.dist-info/entry_points.txt
jupyter_remote_desktop_proxy-3.0.1.dist-info/top_level.txt
jupyter_remote_desktop_proxy-3.0.1.dist-info/RECORD
