Metadata-Version: 2.4
Name: jupyter-remote-desktop-proxy
Version: 3.0.1
Summary: Run a desktop environments on Jupyter
Home-page: https://jupyter.org
Author: Jupyter Development Team
Author-email: jupyter@googlegroups.com
License: BSD
Project-URL: Source, https://github.com/jupyterhub/jupyter-remote-desktop-proxy/
Project-URL: Tracker, https://github.com/jupyterhub/jupyter-remote-desktop-proxy/issues
Keywords: Interactive,Desktop,Jupyter
Platform: Linux
Classifier: Intended Audience :: Developers
Classifier: Intended Audience :: System Administrators
Classifier: Intended Audience :: Science/Research
Classifier: License :: OSI Approved :: BSD License
Classifier: Programming Language :: Python
Classifier: Programming Language :: Python :: 3
Requires-Python: >=3.8
License-File: LICENSE
Requires-Dist: jupyter-server-proxy>=4.3.0
Dynamic: author
Dynamic: author-email
Dynamic: classifier
Dynamic: description
Dynamic: description-content-type
Dynamic: home-page
Dynamic: keywords
Dynamic: license
Dynamic: license-file
Dynamic: platform
Dynamic: project-url
Dynamic: requires-dist
Dynamic: requires-python
Dynamic: summary
